adb_tool_py/__init__.py
adb_tool_py/adb_command.py
adb_tool_py/adb_device.py
adb_tool_py/adb_image_cv.py
adb_tool_py/adb_tool.py
adb_tool_py/adb_view_tree.py
adb_tool_py/command.py
adb_tool_py/ui_node.py
adb_tool_py-0.1.2.dist-info/LICENSE
adb_tool_py-0.1.2.dist-info/METADATA
adb_tool_py-0.1.2.dist-info/WHEEL
adb_tool_py-0.1.2.dist-info/top_level.txt
adb_tool_py-0.1.2.dist-info/RECORD
